ultrasync/__init__.py
ultrasync/cli.py
ultrasync/common.py
ultrasync/config.py
ultrasync/logger.py
ultrasync/main.py
ultrasync-1.0.3.dist-info/LICENSE
ultrasync-1.0.3.dist-info/METADATA
ultrasync-1.0.3.dist-info/WHEEL
ultrasync-1.0.3.dist-info/entry_points.txt
ultrasync-1.0.3.dist-info/top_level.txt
ultrasync-1.0.3.dist-info/RECORD
