Metadata-Version: 2.1
Name: ultrasync
Version: 1.0.3
Summary: Wrapper to XGen/XGen8/ComNav/Hills/Interlogix NX-595E/UltraSync ZeroWire
Home-page: https://github.com/caronc/ultrasync
Author: Chris Caron
Author-email: lead2gold@gmail.com
License: MIT
Keywords: XGen XGen8 Hills Aritech ComNav Interlogix UltraSync NX-595E ZeroWire Security Panel
Classifier: Development Status :: 5 - Production/Stable
Classifier: Intended Audience :: Developers
Classifier: Intended Audience :: System Administrators
Classifier: Operating System :: OS Independent
Classifier: Natural Language :: English
Classifier: Programming Language :: Python
Classifier: Programming Language :: Python :: 3
Classifier: License :: OSI Approved :: MIT License
Classifier: Topic :: Software Development :: Libraries :: Python Modules
Classifier: Topic :: Software Development :: Libraries :: Application Frameworks
Requires-Python: >=3.7
License-File: LICENSE
Requires-Dist: click
Requires-Dist: requests
